MANIFEST.in
README.rst
setup.cfg
setup.py
django_dnoticias_utils.egg-info/PKG-INFO
django_dnoticias_utils.egg-info/SOURCES.txt
django_dnoticias_utils.egg-info/dependency_links.txt
django_dnoticias_utils.egg-info/requires.txt
django_dnoticias_utils.egg-info/top_level.txt
dnoticias_utils/__init__.py
dnoticias_utils/apps.py
dnoticias_utils/error_views.py
dnoticias_utils/hash.py
dnoticias_utils/mixins.py
dnoticias_utils/models.py
dnoticias_utils/singleton.py
dnoticias_utils/utilities.py
dnoticias_utils/views.py
dnoticias_utils/__pycache__/__init__.cpython-310.pyc
dnoticias_utils/__pycache__/__init__.cpython-37.pyc
dnoticias_utils/__pycache__/__init__.cpython-39.pyc
dnoticias_utils/__pycache__/apps.cpython-310.pyc
dnoticias_utils/__pycache__/apps.cpython-39.pyc
dnoticias_utils/__pycache__/error_views.cpython-310.pyc
dnoticias_utils/__pycache__/error_views.cpython-37.pyc
dnoticias_utils/__pycache__/error_views.cpython-39.pyc
dnoticias_utils/__pycache__/hash.cpython-310.pyc
dnoticias_utils/__pycache__/hash.cpython-37.pyc
dnoticias_utils/__pycache__/hash.cpython-39.pyc
dnoticias_utils/__pycache__/mixins.cpython-310.pyc
dnoticias_utils/__pycache__/models.cpython-310.pyc
dnoticias_utils/__pycache__/models.cpython-37.pyc
dnoticias_utils/__pycache__/models.cpython-39.pyc
dnoticias_utils/__pycache__/singleton.cpython-310.pyc
dnoticias_utils/__pycache__/singleton.cpython-37.pyc
dnoticias_utils/__pycache__/singleton.cpython-39.pyc
dnoticias_utils/__pycache__/utilities.cpython-310.pyc
dnoticias_utils/__pycache__/utilities.cpython-37.pyc
dnoticias_utils/__pycache__/utilities.cpython-39.pyc
dnoticias_utils/__pycache__/views.cpython-310.pyc
dnoticias_utils/__pycache__/views.cpython-37.pyc
dnoticias_utils/__pycache__/views.cpython-39.pyc
dnoticias_utils/performance/num_queries.py
dnoticias_utils/performance/sql_queries.py
dnoticias_utils/performance/timer.py
dnoticias_utils/templates/__init__.py
dnoticias_utils/templates/error.html
dnoticias_utils/templatetags/base.py
dnoticias_utils/templatetags/date.py
dnoticias_utils/templatetags/debug.py
dnoticias_utils/templatetags/form.py
dnoticias_utils/templatetags/format_number.py
dnoticias_utils/templatetags/math.py
dnoticias_utils/templatetags/query.py
